{"Paesano": [], "Sabrina's Restaurant": [], "Buca di Beppo Italian Restaurant": [], "Vino": [], "Arancino on Beachwalk": [], "Amina Pizzeria": [], "Sarentos Top of the Ilikai": [], "Bernini Honolulu": [], "Arancino at The Kahala": [], "HASR Bistro": [], "Win-Spuntino": [], "Formaggio": [], "Il Lupino Trattoria & Wine Bar": [], "Bellini Bistro & Bar": [], "La Cucina Ristorante Italiano": [], "Taormina Sicilian Cuisine": [], "Sistina": [], "Assaggio Ristorante Italiano": [], "Assaggio Bistro": [], "Arancino di Mare": []}